LICENSE
MANIFEST.in
README.rst
setup.py
input/data/tdistribution.csv
sample/__init__.py
sample/core.py
sample/helpers.py
statstester/__init__.py
statstester/statstester.py