Metadata-Version: 1.0
Name: statstester
Version: 1.1.3
Summary: Supporting Statistical Test.
Home-page: https://github.com/montblanc18
Author: Shin Kurita
Author-email: UNKNOWN
License: MIT
Platform: UNKNOWN
